setup.py
payment_card_identifier/__init__.py
payment_card_identifier/card.py
payment_card_identifier/constant.py
payment_card_identifier/identifier.py
payment_card_identifier.egg-info/PKG-INFO
payment_card_identifier.egg-info/SOURCES.txt
payment_card_identifier.egg-info/dependency_links.txt
payment_card_identifier.egg-info/top_level.txt
test/test_card.py
test/test_identifier.py