Metadata-Version: 1.1
Name: payment-card-identifier
Version: 0.1.2
Summary: Payment card identifier provides a useful utility method for determining a credit card type from both fully qualified and partial numbers.
Home-page: https://github.com/Ousret/payment-card-identifier
Author: Ahmed TAHRI, @Ousret
Author-email: ahmed@tahri.space
License: MIT
Download-URL: https://github.com/Ousret/payment-card-identifier/archive/0.1.2.tar.gz
Keywords: payment,credit card,debit card,visa,mastercard,merchant,pos,amex,card type identifier
Platform: UNKNOWN
Classifier: Development Status :: 5 - Production/Stable
Classifier: Environment :: Win32 (MS Windows)
Classifier: Environment :: X11 Applications
Classifier: Environment :: MacOS X
Classifier: Intended Audience :: Developers
Classifier: License :: OSI Approved :: BSD License
Classifier: Operating System :: OS Independent
Classifier: Programming Language :: Python
Classifier: Programming Language :: Python :: 2.7
Classifier: Programming Language :: Python :: 3
Classifier: Programming Language :: Python :: 3.1
Classifier: Programming Language :: Python :: 3.2
Classifier: Programming Language :: Python :: 3.3
Classifier: Programming Language :: Python :: 3.4
Classifier: Programming Language :: Python :: 3.5
Classifier: Programming Language :: Python :: 3.6
